xoverrr/__init__.py
xoverrr/constants.py
xoverrr/core.py
xoverrr/exceptions.py
xoverrr/logger.py
xoverrr/models.py
xoverrr/utils.py
xoverrr/adapters/__init__.py
xoverrr/adapters/base.py
xoverrr/adapters/clickhouse.py
xoverrr/adapters/oracle.py
xoverrr/adapters/postgres.py
xoverrr-1.1.4.dist-info/licenses/LICENSE
xoverrr-1.1.4.dist-info/METADATA
xoverrr-1.1.4.dist-info/WHEEL
xoverrr-1.1.4.dist-info/top_level.txt
xoverrr-1.1.4.dist-info/RECORD
