Metadata-Version: 2.4
Name: xoverrr
Version: 1.1.4
Summary: A tool for cross-database and intra-source data comparison with detailed discrepancy analysis and reporting.
Author-email: Dmitry Ischenko <hotmori@gmail.com>
License: MIT
Project-URL: Homepage, https://github.com/dima-ischenko/xoverrr
Keywords: data-quality,comparison,database,data,quality,engineering
Classifier: Intended Audience :: Developers
Classifier: Topic :: Database
Classifier: License :: OSI Approved :: MIT License
Requires-Python: >=3.9
License-File: LICENSE
Requires-Dist: pandas>=2.0.0
Requires-Dist: sqlalchemy>=2.0.0
Requires-Dist: numpy>=1.24.0
Requires-Dist: oracledb>=2.0.0
Requires-Dist: psycopg2-binary>=2.9.0
Requires-Dist: clickhouse-sqlalchemy>=0.2.0
Provides-Extra: dev
Requires-Dist: pytest>=7.0.0; extra == "dev"
Requires-Dist: pytest-cov>=4.0.0; extra == "dev"
Requires-Dist: black>=23.0.0; extra == "dev"
Requires-Dist: isort>=5.12.0; extra == "dev"
Requires-Dist: mypy>=1.0.0; extra == "dev"
Requires-Dist: pre-commit>=3.0.0; extra == "dev"
Requires-Dist: tenacity>=8.2.0; extra == "dev"
Provides-Extra: test
Requires-Dist: pytest>=7.0.0; extra == "test"
Requires-Dist: pytest-cov>=4.0.0; extra == "test"
Requires-Dist: tenacity>=8.2.0; extra == "test"
Provides-Extra: lint
Requires-Dist: black>=23.0.0; extra == "lint"
Requires-Dist: isort>=5.12.0; extra == "lint"
Requires-Dist: flake8>=6.0.0; extra == "lint"
Dynamic: license-file
